{
  "statuscode":1,
  "data":[
    {
      "oid":"1",
      "gongsimingzi":"不知道",
      "param1":"哈市不知道",
      "param2":"123",
      "param3":"1234",
      "param4":"45234",
      "param5":"534",
      "param6":"2342134",
      "param7":"234123",
      "param8":"24312",
      "param9":"2342",
      "param10":"341",
      "param11":"532",
      "param12":"21234"
    },
    {
      "oid":"2",
      "gongsimingzi":"2",
      "param1":"哈市不知道",
      "param2":"123",
      "param3":"1234",
      "param4":"45234",
      "param5":"534",
      "param6":"2342134",
      "param7":"234123",
      "param8":"24312",
      "param9":"2342",
      "param10":"341",
      "param11":"532",
      "param12":"21234"
    },
    {
      "oid":"3",
      "gongsimingzi":"3",
      "param1":"哈市不知道",
      "param2":"123",
      "param3":"1234",
      "param4":"45234",
      "param5":"534",
      "param6":"2342134",
      "param7":"234123",
      "param8":"24312",
      "param9":"2342",
      "param10":"341",
      "param11":"532",
      "param12":"21234"
    },
    {
      "oid":"4",
      "gongsimingzi":"4",
      "param1":"哈市不知道",
      "param2":"123",
      "param3":"1234",
      "param4":"45234",
      "param5":"534",
      "param6":"2342134",
      "param7":"234123",
      "param8":"24312",
      "param9":"2342",
      "param10":"341",
      "param11":"532",
      "param12":"21234"
    },
    {
      "oid":"5",
      "gongsimingzi":"5",
      "param1":"哈市不知道",
      "param2":"123",
      "param3":"1234",
      "param4":"45234",
      "param5":"534",
      "param6":"2342134",
      "param7":"234123",
      "param8":"24312",
      "param9":"2342",
      "param10":"341",
      "param11":"532",
      "param12":"21234"
    },
    {
      "oid":"6",
      "gongsimingzi":"6",
      "param1":"哈市不知道",
      "param2":"123",
      "param3":"1234",
      "param4":"45234",
      "param5":"534",
      "param6":"2342134",
      "param7":"234123",
      "param8":"24312",
      "param9":"2342",
      "param10":"341",
      "param11":"532",
      "param12":"21234"
    },
    {
      "oid":"7",
      "gongsimingzi":"7",
      "param1":"哈市不知道",
      "param2":"123",
      "param3":"1234",
      "param4":"45234",
      "param5":"534",
      "param6":"2342134",
      "param7":"234123",
      "param8":"24312",
      "param9":"2342",
      "param10":"341",
      "param11":"532",
      "param12":"21234"
    },
    {
      "oid":"8",
      "gongsimingzi":"8",
      "param1":"哈市不知道",
      "param2":"123",
      "param3":"1234",
      "param4":"45234",
      "param5":"534",
      "param6":"2342134",
      "param7":"234123",
      "param8":"24312",
      "param9":"2342",
      "param10":"341",
      "param11":"532",
      "param12":"21234"
    },
    {
      "oid":"9",
      "gongsimingzi":"9",
      "param1":"哈市不知道",
      "param2":"123",
      "param3":"1234",
      "param4":"45234",
      "param5":"534",
      "param6":"2342134",
      "param7":"234123",
      "param8":"24312",
      "param9":"2342",
      "param10":"341",
      "param11":"532",
      "param12":"21234"
    },
    {
      "oid":"10",
      "gongsimingzi":"10",
      "param1":"哈市不知道",
      "param2":"123",
      "param3":"1234",
      "param4":"45234",
      "param5":"534",
      "param6":"2342134",
      "param7":"234123",
      "param8":"24312",
      "param9":"2342",
      "param10":"341",
      "param11":"532",
      "param12":"21234"
    },
    {
      "oid":"11",
      "gongsimingzi":"11",
      "param1":"哈市不知道",
      "param2":"123",
      "param3":"1234",
      "param4":"45234",
      "param5":"534",
      "param6":"2342134",
      "param7":"234123",
      "param8":"24312",
      "param9":"2342",
      "param10":"341",
      "param11":"532",
      "param12":"21234"
    },
    {
      "oid":"12",
      "gongsimingzi":"12",
      "param1":"哈市不知道",
      "param2":"123",
      "param3":"1234",
      "param4":"45234",
      "param5":"534",
      "param6":"2342134",
      "param7":"234123",
      "param8":"24312",
      "param9":"2342",
      "param10":"341",
      "param11":"532",
      "param12":"21234"
    },
    {
      "oid":"12",
      "gongsimingzi":"12",
      "param1":"哈市不知道",
      "param2":"123",
      "param3":"1234",
      "param4":"45234",
      "param5":"534",
      "param6":"2342134",
      "param7":"234123",
      "param8":"24312",
      "param9":"2342",
      "param10":"341",
      "param11":"532",
      "param12":"21234"
    },
    {
      "oid":"13",
      "gongsimingzi":"13",
      "param1":"哈市不知道",
      "param2":"123",
      "param3":"1234",
      "param4":"45234",
      "param5":"534",
      "param6":"2342134",
      "param7":"234123",
      "param8":"24312",
      "param9":"2342",
      "param10":"341",
      "param11":"532",
      "param12":"21234"
    },
    {
      "oid":"14",
      "gongsimingzi":"14",
      "param1":"哈市不知道",
      "param2":"123",
      "param3":"1234",
      "param4":"45234",
      "param5":"534",
      "param6":"2342134",
      "param7":"234123",
      "param8":"24312",
      "param9":"2342",
      "param10":"341",
      "param11":"532",
      "param12":"21234"
    },
    {
      "oid":"15",
      "gongsimingzi":"15",
      "param1":"哈市不知道",
      "param2":"123",
      "param3":"1234",
      "param4":"45234",
      "param5":"534",
      "param6":"2342134",
      "param7":"234123",
      "param8":"24312",
      "param9":"2342",
      "param10":"341",
      "param11":"532",
      "param12":"21234"
    },
    {
      "oid":"16",
      "gongsimingzi":"16",
      "param1":"哈市不知道",
      "param2":"123",
      "param3":"1234",
      "param4":"45234",
      "param5":"534",
      "param6":"2342134",
      "param7":"234123",
      "param8":"24312",
      "param9":"2342",
      "param10":"341",
      "param11":"532",
      "param12":"21234"
    }
  ]
}